{
  "people": [
    {
      "id": "wesley-kamau",
      "name": "Wesley Kamau",
      "description": "Me!",
      "category": "interns",
      "individualPhoto": null,
      "photoLocations": [
        {
          "photoId": "pathways-photo",
          "x": 69.08,
          "y": 42.29,
          "width": 12.53,
          "height": 9.4,
          "rotation": 107
        },
        {
          "photoId": "family-photo",
          "x": 68.67,
          "y": 13.32,
          "width": 15.11,
          "height": 20.15,
          "rotation": 11
        },
        {
          "photoId": "interns-photo",
          "x": 28.01,
          "y": 54.06,
          "width": 3.99,
          "height": 6.5
        },
        {
          "photoId": "staff-photo",
          "x": 38.99,
          "y": 18.23,
          "width": 7.39,
          "height": 5.54
        }
      ],
      "preferredPhotoId": "family-photo"
    },
    {
      "id": "jonathan-mickelson",
      "name": "Jonathan Mickelson",
      "description": "Best mentor",
      "category": "staff",
      "individualPhoto": null,
      "linkedIn": "https://www.linkedin.com/in/jonathanmickelson/",
      "photoLocations": [
        {
          "photoId": "family-photo",
          "x": 10.89,
          "y": 13.63,
          "width": 17.99,
          "height": 23.99
        },
        {
          "photoId": "staff-photo",
          "x": 44.96,
          "y": 20.37,
          "width": 8.87,
          "height": 6.65
        }
      ],
      "preferredPhotoId": "family-photo"
    },
    {
      "id": "amanda-solomon",
      "name": "Amanda Solomon",
      "description": "",
      "category": "interns",
      "individualPhoto": null,
      "photoLocations": [
        {
          "photoId": "pathways-photo",
          "x": 30.7,
          "y": 65.62,
          "width": 12.09,
          "height": 9.07,
          "rotation": 349
        },
        {
          "photoId": "interns-photo",
          "x": 50.28,
          "y": 55.88,
          "width": 4.41,
          "height": 6.37
        }
      ],
      "preferredPhotoId": "interns-photo"
    },
    {
      "id": "randall-tomlinson",
      "name": "Randall Tomlinson",
      "description": "",
      "category": "interns",
      "individualPhoto": null,
      "photoLocations": [
        {
          "photoId": "pathways-photo",
          "x": 20.48,
          "y": 63.64,
          "width": 12.02,
          "height": 9.01,
          "rotation": 331
        },
        {
          "photoId": "interns-photo",
          "x": 70.21,
          "y": 55.7,
          "width": 4.72,
          "height": 6.84
        }
      ],
      "preferredPhotoId": "interns-photo"
    },
    {
      "id": "aadarsh-arasu",
      "name": "Aadarsh Arasu",
      "description": "",
      "category": "interns",
      "individualPhoto": null,
      "photoLocations": [
        {
          "photoId": "pathways-photo",
          "x": 71.65,
          "y": 31.84,
          "width": 13.99,
          "height": 10.49,
          "rotation": 127
        },
        {
          "photoId": "interns-photo",
          "x": 75.38,
          "y": 56.3,
          "width": 4.93,
          "height": 7.14,
          "rotation": 9
        }
      ],
      "preferredPhotoId": "interns-photo"
    },
    {
      "id": "viri-cobos",
      "name": "Viri Cobos",
      "description": "",
      "category": "interns",
      "individualPhoto": null,
      "photoLocations": [
        {
          "photoId": "pathways-photo",
          "x": 12.99,
          "y": 27.66,
          "width": 11.51,
          "height": 8.63,
          "rotation": 232
        }
      ],
      "preferredPhotoId": "pathways-photo"
    },
    {
      "id": "joeseph-osgood",
      "name": "Joeseph Osgood",
      "description": "",
      "category": "interns",
      "individualPhoto": null,
      "photoLocations": [
        {
          "photoId": "pathways-photo",
          "x": 15.76,
          "y": 35.58,
          "width": 12.24,
          "height": 9.18,
          "rotation": 254
        }
      ],
      "preferredPhotoId": "pathways-photo"
    },
    {
      "id": "brody-hollensteiner",
      "name": "Brody Hollensteiner",
      "description": "",
      "category": "interns",
      "individualPhoto": null,
      "photoLocations": [
        {
          "photoId": "pathways-photo",
          "x": 17.58,
          "y": 43.84,
          "width": 12.38,
          "height": 9.29,
          "rotation": 274
        }
      ],
      "preferredPhotoId": "pathways-photo"
    },
    {
      "id": "jimi-k-daniel",
      "name": "Jimi-K Daniel",
      "description": "",
      "category": "interns",
      "individualPhoto": null,
      "photoLocations": [
        {
          "photoId": "pathways-photo",
          "x": 12.4,
          "y": 53.64,
          "width": 13.62,
          "height": 10.22,
          "rotation": 280
        }
      ],
      "preferredPhotoId": "pathways-photo"
    },
    {
      "id": "siddarth-sambath",
      "name": "Siddarth Sambath",
      "description": "",
      "category": "interns",
      "individualPhoto": null,
      "photoLocations": [
        {
          "photoId": "pathways-photo",
          "x": 11.54,
          "y": 62.25,
          "width": 11.59,
          "height": 8.57,
          "rotation": 302
        }
      ],
      "preferredPhotoId": "pathways-photo"
    },
    {
      "id": "lauren-vic-paulson",
      "name": "Lauren \"Vic\" Paulson",
      "description": "",
      "category": "interns",
      "individualPhoto": null,
      "photoLocations": [
        {
          "photoId": "pathways-photo",
          "x": 42.58,
          "y": 63.81,
          "width": 13.04,
          "height": 9.78,
          "rotation": 359
        }
      ],
      "preferredPhotoId": "pathways-photo"
    },
    {
      "id": "jennifer-trainor",
      "name": "Jennifer Trainor",
      "description": "",
      "category": "interns",
      "individualPhoto": null,
      "photoLocations": [
        {
          "photoId": "pathways-photo",
          "x": 54.72,
          "y": 63.67,
          "width": 12.89,
          "height": 9.67,
          "rotation": 19
        }
      ],
      "preferredPhotoId": "pathways-photo"
    },
    {
      "id": "tanmayee-udas",
      "name": "Tanmayee Udas",
      "description": "",
      "category": "interns",
      "individualPhoto": null,
      "photoLocations": [
        {
          "photoId": "pathways-photo",
          "x": 64.95,
          "y": 62.24,
          "width": 13.84,
          "height": 10.38,
          "rotation": 44
        }
      ],
      "preferredPhotoId": "pathways-photo"
    },
    {
      "id": "aman-anas",
      "name": "Aman Anas",
      "description": "",
      "category": "interns",
      "individualPhoto": null,
      "photoLocations": [
        {
          "photoId": "pathways-photo",
          "x": 78.84,
          "y": 60.21,
          "width": 12.97,
          "height": 9.72,
          "rotation": 49
        }
      ],
      "preferredPhotoId": "pathways-photo"
    },
    {
      "id": "austin-salmon",
      "name": "Austin Salmon",
      "description": "",
      "category": "interns",
      "individualPhoto": null,
      "photoLocations": [
        {
          "photoId": "pathways-photo",
          "x": 78.25,
          "y": 50.87,
          "width": 12.53,
          "height": 9.4,
          "rotation": 85
        }
      ],
      "preferredPhotoId": "pathways-photo"
    },
    {
      "id": "arjun-pandiarajan",
      "name": "Arjun Pandiarajan",
      "description": "",
      "category": "interns",
      "individualPhoto": null,
      "photoLocations": [
        {
          "photoId": "pathways-photo",
          "x": 60.78,
          "y": 28.27,
          "width": 12.97,
          "height": 9.72,
          "rotation": 149
        }
      ],
      "preferredPhotoId": "pathways-photo"
    },
    {
      "id": "ethan-jones",
      "name": "Ethan Jones",
      "description": "",
      "category": "interns",
      "individualPhoto": null,
      "photoLocations": [
        {
          "photoId": "pathways-photo",
          "x": 48.82,
          "y": 26.8,
          "width": 13.26,
          "height": 9.94,
          "rotation": 167
        }
      ],
      "preferredPhotoId": "pathways-photo"
    },
    {
      "id": "urban-michaels",
      "name": "Urban Michaels",
      "description": "",
      "category": "interns",
      "individualPhoto": null,
      "photoLocations": [
        {
          "photoId": "pathways-photo",
          "x": 28.51,
          "y": 20.57,
          "width": 11.87,
          "height": 8.91,
          "rotation": 199
        }
      ],
      "preferredPhotoId": "pathways-photo"
    },
    {
      "id": "roman-basset",
      "name": "Roman Basset",
      "description": "",
      "category": "interns",
      "individualPhoto": null,
      "photoLocations": [
        {
          "photoId": "pathways-photo",
          "x": 23.32,
          "y": 25.6,
          "width": 11.8,
          "height": 8.85,
          "rotation": 216
        }
      ],
      "preferredPhotoId": "pathways-photo"
    },
    {
      "id": "stephen-zurawick",
      "name": "Stephen Zurawick",
      "description": "",
      "category": "interns",
      "individualPhoto": null,
      "photoLocations": [
        {
          "photoId": "pathways-photo",
          "x": 39.42,
          "y": 23.8,
          "width": 10.74,
          "height": 8.05,
          "rotation": 184
        }
      ],
      "preferredPhotoId": "pathways-photo"
    },
    {
      "id": "mom",
      "name": "Susan",
      "description": "My mom",
      "category": "family",
      "individualPhoto": null,
      "photoLocations": [
        {
          "photoId": "family-photo",
          "x": 27.86,
          "y": 31.21,
          "width": 14.9,
          "height": 19.87
        }
      ],
      "preferredPhotoId": "family-photo"
    },
    {
      "id": "maureen",
      "name": "Maureen",
      "description": "My sister",
      "category": "family",
      "individualPhoto": null,
      "photoLocations": [
        {
          "photoId": "family-photo",
          "x": 42.21,
          "y": 27.28,
          "width": 14.7,
          "height": 19.6
        }
      ],
      "preferredPhotoId": "family-photo"
    },
    {
      "id": "dad",
      "name": "Stephen",
      "description": "My dad",
      "category": "family",
      "individualPhoto": null,
      "photoLocations": [
        {
          "photoId": "family-photo",
          "x": 55.19,
          "y": 16.38,
          "width": 15.73,
          "height": 20.97
        }
      ],
      "preferredPhotoId": "family-photo"
    },
    {
      "id": "maddy-stratton",
      "name": "Maddy Stratton",
      "description": "",
      "category": "interns",
      "individualPhoto": null,
      "photoLocations": [
        {
          "photoId": "interns-photo",
          "x": 14.71,
          "y": 56.85,
          "width": 3.23,
          "height": 4.95
        }
      ],
      "preferredPhotoId": "interns-photo"
    },
    {
      "id": "emma-hansen",
      "name": "Emma Hansen",
      "description": "",
      "category": "interns",
      "individualPhoto": null,
      "photoLocations": [
        {
          "photoId": "interns-photo",
          "x": 17.77,
          "y": 58.86,
          "width": 3.43,
          "height": 5.15
        }
      ],
      "preferredPhotoId": "interns-photo"
    },
    {
      "id": "catherine-franco",
      "name": "Catherine Franco",
      "description": "",
      "category": "interns",
      "individualPhoto": null,
      "photoLocations": [
        {
          "photoId": "interns-photo",
          "x": 20.54,
          "y": 59.62,
          "width": 3.76,
          "height": 5.39
        }
      ],
      "preferredPhotoId": "interns-photo"
    },
    {
      "id": "achyut-shrestha",
      "name": "Achyut Shrestha",
      "description": "",
      "category": "interns",
      "individualPhoto": null,
      "photoLocations": [
        {
          "photoId": "interns-photo",
          "x": 31.76,
          "y": 67.43,
          "width": 4.11,
          "height": 5.91
        }
      ],
      "preferredPhotoId": "interns-photo"
    },
    {
      "id": "alex-vance",
      "name": "Alex Vance",
      "description": "",
      "category": "interns",
      "individualPhoto": null,
      "photoLocations": [
        {
          "photoId": "interns-photo",
          "x": 32.56,
          "y": 55.88,
          "width": 3.43,
          "height": 5.15
        }
      ],
      "preferredPhotoId": "interns-photo"
    },
    {
      "id": "angelica-hunter",
      "name": "Angelica Hunter",
      "description": "",
      "category": "interns",
      "individualPhoto": null,
      "photoLocations": [
        {
          "photoId": "interns-photo",
          "x": 35.96,
          "y": 56.91,
          "width": 3.4,
          "height": 5.1
        }
      ],
      "preferredPhotoId": "interns-photo"
    },
    {
      "id": "sarah-bloom",
      "name": "Sarah Bloom",
      "description": "",
      "category": "interns",
      "individualPhoto": null,
      "linkedIn": "https://www.linkedin.com/in/sarah-bloom/",
      "photoLocations": [
        {
          "photoId": "interns-photo",
          "x": 37.72,
          "y": 67.11,
          "width": 4.12,
          "height": 6.18
        }
      ],
      "preferredPhotoId": "interns-photo"
    },
    {
      "id": "bradley-gartner",
      "name": "Bradley Gartner",
      "description": "",
      "category": "interns",
      "individualPhoto": null,
      "linkedIn": "https://www.linkedin.com/in/bradley-gartner-77820b185/",
      "photoLocations": [
        {
          "photoId": "interns-photo",
          "x": 49.75,
          "y": 70.25,
          "width": 5.01,
          "height": 7.52
        }
      ],
      "preferredPhotoId": "interns-photo"
    },
    {
      "id": "isai-andrade",
      "name": "Isai Andrade",
      "description": "",
      "category": "interns",
      "individualPhoto": null,
      "photoLocations": [
        {
          "photoId": "interns-photo",
          "x": 80.77,
          "y": 57.28,
          "width": 4.93,
          "height": 7.14
        }
      ],
      "preferredPhotoId": "interns-photo"
    },
    {
      "id": "armando-cardona",
      "name": "Armando Cardona",
      "description": "",
      "category": "interns",
      "individualPhoto": null,
      "photoLocations": [
        {
          "photoId": "interns-photo",
          "x": 23.76,
          "y": 55.18,
          "width": 4.33,
          "height": 6.49
        }
      ],
      "preferredPhotoId": "interns-photo"
    },
    {
      "id": "hannah-epstein",
      "name": "Hannah Epstein",
      "description": "",
      "category": "interns",
      "individualPhoto": null,
      "photoLocations": [
        {
          "photoId": "interns-photo",
          "x": 10.43,
          "y": 57.35,
          "width": 4.05,
          "height": 6.07
        }
      ],
      "preferredPhotoId": "interns-photo"
    },
    {
      "id": "jason-beals",
      "name": "Jason Beals",
      "description": "",
      "category": "interns",
      "individualPhoto": null,
      "photoLocations": [
        {
          "photoId": "interns-photo",
          "x": 43.7,
          "y": 54.18,
          "width": 5.47,
          "height": 8.21
        }
      ],
      "preferredPhotoId": "interns-photo"
    },
    {
      "id": "luke-kiziah",
      "name": "Luke Kiziah",
      "description": "",
      "category": "interns",
      "individualPhoto": null,
      "photoLocations": [
        {
          "photoId": "interns-photo",
          "x": 60.88,
          "y": 55.9,
          "width": 4.09,
          "height": 6.13
        }
      ],
      "preferredPhotoId": "interns-photo"
    },
    {
      "id": "miguel-a-vasquez-lopez",
      "name": "Miguel A. Vasquez Lopez",
      "description": "",
      "category": "interns",
      "individualPhoto": null,
      "photoLocations": [
        {
          "photoId": "interns-photo",
          "x": 40.31,
          "y": 54.57,
          "width": 4.31,
          "height": 6.21
        }
      ],
      "preferredPhotoId": "interns-photo"
    },
    {
      "id": "natalie-ayala",
      "name": "Natalie Ayala",
      "description": "",
      "category": "interns",
      "individualPhoto": null,
      "photoLocations": [
        {
          "photoId": "interns-photo",
          "x": 58.62,
          "y": 69.11,
          "width": 4.67,
          "height": 6.75
        }
      ],
      "preferredPhotoId": "interns-photo"
    },
    {
      "id": "tiarra-smith",
      "name": "Tiarra Smith",
      "description": "",
      "category": "interns",
      "individualPhoto": null,
      "photoLocations": [
        {
          "photoId": "interns-photo",
          "x": 45.05,
          "y": 69.12,
          "width": 4.77,
          "height": 7.15
        }
      ],
      "preferredPhotoId": "interns-photo"
    },
    {
      "id": "william-armentrout",
      "name": "William Armentrout",
      "description": "",
      "category": "interns",
      "individualPhoto": null,
      "photoLocations": [
        {
          "photoId": "interns-photo",
          "x": 18.7,
          "y": 55.5,
          "width": 3.81,
          "height": 5.71
        }
      ],
      "preferredPhotoId": "interns-photo"
    },
    {
      "id": "-roger-baird",
      "name": "Roger Baird",
      "description": "",
      "category": "staff",
      "individualPhoto": null,
      "photoLocations": [
        {
          "photoId": "interns-photo",
          "x": 4.2,
          "y": 55.37,
          "width": 5.03,
          "height": 7.55
        }
      ],
      "preferredPhotoId": "interns-photo"
    },
    {
      "id": "-rae-ann-meyer",
      "name": "Rae Ann Meyer",
      "description": "",
      "category": "staff",
      "individualPhoto": null,
      "photoLocations": [
        {
          "photoId": "interns-photo",
          "x": 83.79,
          "y": 55.71,
          "width": 5.55,
          "height": 8.32
        }
      ],
      "preferredPhotoId": "interns-photo"
    },
    {
      "id": "-joseph-pelfrey",
      "name": "Joseph Pelfrey",
      "description": "",
      "category": "staff",
      "individualPhoto": null,
      "photoLocations": [
        {
          "photoId": "interns-photo",
          "x": 89.84,
          "y": 53.1,
          "width": 5.82,
          "height": 8.73
        }
      ],
      "preferredPhotoId": "interns-photo"
    },
    {
      "id": "larry-leopard",
      "name": "Larry Leopard",
      "description": "",
      "category": "staff",
      "individualPhoto": null,
      "photoLocations": [
        {
          "photoId": "interns-photo",
          "x": 11.69,
          "y": 55.09,
          "width": 3.95,
          "height": 5.93
        }
      ],
      "preferredPhotoId": "interns-photo"
    },
    {
      "id": "foster-ragland",
      "name": "Foster Ragland",
      "description": "",
      "category": "interns",
      "individualPhoto": null,
      "photoLocations": [
        {
          "photoId": "interns-photo",
          "x": 55.46,
          "y": 55.2,
          "width": 4.66,
          "height": 6.99
        }
      ],
      "preferredPhotoId": "interns-photo"
    },
    {
      "id": "leigh-martin",
      "name": "Leigh Martin",
      "description": "Best sense of humor",
      "category": "staff",
      "individualPhoto": null,
      "photoLocations": [
        {
          "photoId": "staff-photo",
          "x": 58.59,
          "y": 51.41,
          "width": 13.9,
          "height": 10.8
        }
      ],
      "preferredPhotoId": "staff-photo"
    },
    {
      "id": "mardi-wilkerson",
      "name": "Mardi Wilkerson",
      "description": "Best mentor",
      "category": "staff",
      "individualPhoto": null,
      "linkedIn": "https://www.linkedin.com/in/mardi-wilkerson-b27584247/",
      "photoLocations": [
        {
          "photoId": "staff-photo",
          "x": 25.92,
          "y": 22.26,
          "width": 8.8,
          "height": 6.85
        }
      ],
      "preferredPhotoId": "staff-photo"
    },
    {
      "id": "allison-gregg",
      "name": "Allison Gregg",
      "description": "Best Baker",
      "category": "staff",
      "individualPhoto": null,
      "linkedIn": "https://www.linkedin.com/in/allison-gregg-acc/",
      "photoLocations": [
        {
          "photoId": "staff-photo",
          "x": 54.74,
          "y": 40.66,
          "width": 12.8,
          "height": 9.72
        }
      ],
      "preferredPhotoId": "staff-photo"
    },
    {
      "id": "april-troutt",
      "name": "April Troutt",
      "description": "One of the nicest people I've ever met",
      "category": "staff",
      "individualPhoto": null,
      "photoLocations": [
        {
          "photoId": "staff-photo",
          "x": 43.95,
          "y": 33.28,
          "width": 10.65,
          "height": 8.24
        }
      ],
      "preferredPhotoId": "staff-photo"
    },
    {
      "id": "kirk-pierce",
      "name": "Kirk Pierce",
      "description": "Most Honest",
      "category": "staff",
      "individualPhoto": null,
      "photoLocations": [
        {
          "photoId": "staff-photo",
          "x": 11.69,
          "y": 14.99,
          "width": 8.56,
          "height": 6.67
        }
      ],
      "preferredPhotoId": "staff-photo"
    },
    {
      "id": "cassandra-gideon",
      "name": "Cassandra Gideon",
      "description": "Most relatable",
      "category": "staff",
      "individualPhoto": null,
      "linkedIn": "https://www.linkedin.com/in/cassandra-gideon-m-s-88976450/",
      "photoLocations": [
        {
          "photoId": "staff-photo",
          "x": 18.34,
          "y": 46.36,
          "width": 12.41,
          "height": 9.3
        }
      ],
      "preferredPhotoId": "staff-photo"
    },
    {
      "id": "jenna-hassell",
      "name": "Jenna Hassell",
      "description": "Most Creative",
      "category": "staff",
      "individualPhoto": null,
      "linkedIn": "https://www.linkedin.com/in/jenna-wilson-hassell/",
      "photoLocations": [
        {
          "photoId": "staff-photo",
          "x": 31.38,
          "y": 46.26,
          "width": 13.31,
          "height": 10.1
        }
      ],
      "preferredPhotoId": "staff-photo"
    },
    {
      "id": "jeramie-broadway",
      "name": "Jeramie Broadway",
      "description": "Best Suits",
      "category": "staff",
      "individualPhoto": null,
      "photoLocations": [
        {
          "photoId": "staff-photo",
          "x": 31.55,
          "y": 17.08,
          "width": 9.77,
          "height": 7.2,
          "rotation": 356
        }
      ],
      "preferredPhotoId": "staff-photo"
    },
    {
      "id": "renee",
      "name": "Renee",
      "description": "My favorite southern accent",
      "category": "staff",
      "individualPhoto": null,
      "photoLocations": [
        {
          "photoId": "staff-photo",
          "x": 20.15,
          "y": 22.14,
          "width": 7.83,
          "height": 5.99
        }
      ],
      "preferredPhotoId": "staff-photo"
    },
    {
      "id": "akia-austin",
      "name": "Akia Austin",
      "description": "Most Helpful",
      "category": "staff",
      "individualPhoto": null,
      "linkedIn": "https://www.linkedin.com/in/akia-a-74a53599/",
      "photoLocations": [
        {
          "photoId": "staff-photo",
          "x": 33.1,
          "y": 32.98,
          "width": 10.42,
          "height": 7.81
        }
      ],
      "preferredPhotoId": "staff-photo"
    },
    {
      "id": "julie-bilbrey",
      "name": "Julie Bilbrey",
      "description": "Most Inspiring Leader",
      "category": "staff",
      "individualPhoto": null,
      "linkedIn": "https://www.linkedin.com/in/julie-bilbrey-01803131/",
      "photoLocations": [
        {
          "photoId": "staff-photo",
          "x": 16.88,
          "y": 15.99,
          "width": 7.9,
          "height": 5.92
        }
      ],
      "preferredPhotoId": "staff-photo"
    },
    {
      "id": "kimberly-newton",
      "name": "Kimberly Newton",
      "description": "Easiest to strike up a conversation with",
      "category": "staff",
      "individualPhoto": null,
      "photoLocations": [
        {
          "photoId": "staff-photo",
          "x": 5.33,
          "y": 11.37,
          "width": 8.36,
          "height": 6.27
        }
      ],
      "preferredPhotoId": "staff-photo"
    },
    {
      "id": "allison-smith",
      "name": "Allison Smith",
      "description": "Always had headphones on, very pleasant to be around",
      "category": "staff",
      "individualPhoto": null,
      "photoLocations": [
        {
          "photoId": "staff-photo",
          "x": 67.19,
          "y": 27.79,
          "width": 10.53,
          "height": 7.9
        }
      ],
      "preferredPhotoId": "staff-photo"
    },
    {
      "id": "hailey-kuhl",
      "name": "Hailey Kuhl",
      "description": "My girlfriend",
      "category": "girlfriend",
      "individualPhoto": null,
      "photoLocations": [
        {
          "photoId": "staff-photo",
          "x": 51.62,
          "y": 30.09,
          "width": 9.44,
          "height": 7.08
        }
      ],
      "preferredPhotoId": "staff-photo"
    },
    {
      "id": "dr.-vemitra-white-alexander",
      "name": "Dr. Vemitra White-Alexander",
      "description": "",
      "category": "staff",
      "individualPhoto": null,
      "photoLocations": [
        {
          "photoId": "staff-photo",
          "x": 36.05,
          "y": 24.24,
          "width": 10.42,
          "height": 7.81
        }
      ],
      "preferredPhotoId": "staff-photo"
    },
    {
      "id": "kathleen-hotchkiss",
      "name": "Kathleen Hotchkiss",
      "description": "",
      "category": "staff",
      "individualPhoto": null,
      "photoLocations": [
        {
          "photoId": "staff-photo",
          "x": 69.5,
          "y": 34.98,
          "width": 8.75,
          "height": 6.56
        }
      ],
      "preferredPhotoId": "staff-photo"
    },
    {
      "id": "gloria-caldwell",
      "name": "Gloria Caldwell",
      "description": "Best Dressed",
      "category": "staff",
      "individualPhoto": "/photos/individual/gloria-caldwell.jpg",
      "photoLocations": []
    },
    {
      "id": "vicky",
      "name": "Vicky",
      "description": "Best sarcasm",
      "category": "staff",
      "individualPhoto": null,
      "photoLocations": []
    },
    {
      "id": "pam-honeycutt",
      "name": "Pam Honeycutt",
      "description": "Tea",
      "category": "staff",
      "individualPhoto": "/photos/individual/pam-honeycutt.jpg",
      "linkedIn": "https://www.linkedin.com/in/kathleen-hotchkiss-mtpc-19531895/",
      "photoLocations": []
    },
    {
      "id": "quincy-bean",
      "name": "Quincy Bean",
      "description": "Coolest Hobby",
      "category": "staff",
      "individualPhoto": "/photos/individual/quincy-bean.jpg",
      "photoLocations": []
    },
    {
      "id": "mandy-pinyan",
      "name": "Mandy Pinyan",
      "description": "Green Thumb",
      "category": "staff",
      "individualPhoto": "/photos/individual/mandy-pinyan.jpg",
      "photoLocations": []
    },
    {
      "id": "janet-anderson",
      "name": "Janet Anderson",
      "description": "Very Thoughtful (thank you note!)",
      "category": "staff",
      "individualPhoto": null,
      "linkedIn": "https://www.linkedin.com/in/janet-anderson-1a30b514/",
      "photoLocations": []
    },
    {
      "id": "beverly-johnson",
      "name": "Beverly Johnson",
      "description": "Best Energy",
      "category": "staff",
      "individualPhoto": "/photos/individual/beverly-johnson.jpg",
      "linkedIn": "https://www.linkedin.com/in/beverlykjohnson/",
      "photoLocations": []
    },
    {
      "id": "michael-smith",
      "name": "Michael Smith",
      "description": "Best Shirts",
      "category": "staff",
      "individualPhoto": "/photos/individual/michael-smith.jpg",
      "photoLocations": []
    },
    {
      "id": "lee-judge",
      "name": "Lee Judge",
      "description": "Inspired me to get a 3D Printer",
      "category": "staff",
      "individualPhoto": "/photos/individual/lee-judge.jpg",
      "photoLocations": []
    },
    {
      "id": "jena-strawn",
      "name": "Jena Strawn",
      "description": "Most patient",
      "category": "staff",
      "individualPhoto": "/photos/individual/jena-rowe.jpg",
      "photoLocations": []
    },
    {
      "id": "shawn-mceniry",
      "name": "Shawn McEniry",
      "description": "Most down-to-earth",
      "category": "staff",
      "individualPhoto": "/photos/individual/shawn-mceniry.jpg",
      "photoLocations": []
    },
    {
      "id": "mary-hovater",
      "name": "Mary Hovater",
      "description": "Coolest office, best boss",
      "category": "staff",
      "individualPhoto": "/photos/individual/mary-hovater.jpg",
      "photoLocations": []
    },
    {
      "id": "melanie-manson",
      "name": "Melanie Manson",
      "description": "Very sweet",
      "category": "staff",
      "individualPhoto": "/photos/individual/melanie-manson.jpg",
      "photoLocations": []
    },
    {
      "id": "brylie-singleton",
      "name": "Brylie Singleton",
      "description": "",
      "category": "interns",
      "individualPhoto": "/photos/individual/brylie-singleton.jpg",
      "photoLocations": []
    },
    {
      "id": "dylan-spano",
      "name": "Dylan Spano",
      "description": "",
      "category": "interns",
      "individualPhoto": null,
      "photoLocations": [],
      "hidden": true
    },
    {
      "id": "ellen-fritz",
      "name": "Ellen Fritz",
      "description": "",
      "category": "interns",
      "individualPhoto": null,
      "photoLocations": [],
      "hidden": true
    },
    {
      "id": "emma-miller",
      "name": "Emma Miller",
      "description": "",
      "category": "interns",
      "individualPhoto": "/photos/individual/emma-miller.jpg",
      "photoLocations": []
    },
    {
      "id": "greyson-wong",
      "name": "Greyson Wong",
      "description": "",
      "category": "interns",
      "individualPhoto": "/photos/individual/greyson-wong.JPG",
      "photoLocations": []
    },
    {
      "id": "isaac-bennett",
      "name": "Isaac Bennett",
      "description": "",
      "category": "interns",
      "individualPhoto": "/photos/individual/isaac-bennett.JPG",
      "photoLocations": []
    },
    {
      "id": "lucas-lothschutz",
      "name": "Lucas Lothschutz",
      "description": "",
      "category": "interns",
      "individualPhoto": null,
      "photoLocations": [],
      "hidden": true
    },
    {
      "id": "mark-platonov",
      "name": "Mark Platonov",
      "description": "",
      "category": "interns",
      "individualPhoto": null,
      "photoLocations": [],
      "hidden": true
    },
    {
      "id": "nikko-baez",
      "name": "Nikko Baez",
      "description": "",
      "category": "interns",
      "individualPhoto": null,
      "photoLocations": [],
      "hidden": true
    },
    {
      "id": "riley-parsons",
      "name": "Riley Parsons",
      "description": "",
      "category": "interns",
      "individualPhoto": null,
      "photoLocations": [],
      "hidden": true
    },
    {
      "id": "sumit-nawathe",
      "name": "Sumit Nawathe",
      "description": "",
      "category": "interns",
      "individualPhoto": null,
      "photoLocations": [],
      "hidden": true
    },
    {
      "id": "talia-frendl",
      "name": "Talia Frendl",
      "description": "",
      "category": "interns",
      "individualPhoto": null,
      "photoLocations": [],
      "hidden": true
    },
    {
      "id": "yousef-alzaybak",
      "name": "Yousef Alzaybak",
      "description": "",
      "category": "interns",
      "individualPhoto": null,
      "photoLocations": [],
      "hidden": true
    },
    {
      "id": "jackson-cho",
      "name": "Jackson Cho",
      "description": "",
      "category": "staff",
      "individualPhoto": "/photos/individual/jackson-cho.jpg",
      "photoLocations": []
    },
    {
      "id": "brian-hoang",
      "name": "Brian Hoang",
      "description": "",
      "category": "staff",
      "individualPhoto": "/photos/individual/brian-hoang.jpg",
      "photoLocations": []
    },
    {
      "id": "andi-johnson",
      "hidden": true,
      "name": "Andi Johnson",
      "description": "",
      "category": "interns",
      "individualPhoto": null,
      "photoLocations": []
    },
    {
      "id": "benjamin-stroup",
      "name": "Benjamin Stroup",
      "description": "",
      "category": "interns",
      "individualPhoto": "/photos/individual/benjamin-stroup.jpg",
      "photoLocations": []
    },
    {
      "id": "claire-w",
      "name": "Claire W",
      "description": "",
      "category": "interns",
      "individualPhoto": "/photos/individual/claire-w.jpg",
      "photoLocations": []
    },
    {
      "id": "ethan-thornton",
      "name": "Ethan Thornton",
      "description": "",
      "category": "interns",
      "individualPhoto": "/photos/individual/ethan-thornton.jpg",
      "photoLocations": []
    },
    {
      "id": "ivy-zhan",
      "name": "Ivy Zhan",
      "description": "",
      "category": "interns",
      "individualPhoto": "/photos/individual/ivy-zhan.jpg",
      "photoLocations": []
    },
    {
      "id": "lux-snyder",
      "name": "Lux Snyder",
      "description": "",
      "category": "interns",
      "individualPhoto": "/photos/individual/lux-snyder.jpg",
      "photoLocations": []
    },
    {
      "id": "michael-j",
      "name": "Michael J",
      "description": "",
      "category": "interns",
      "individualPhoto": "/photos/individual/michael-j.jpg",
      "photoLocations": []
    },
    {
      "id": "sebastian-oviedo",
      "name": "Sebastian Oviedo",
      "description": "",
      "category": "interns",
      "individualPhoto": "/photos/individual/sebastian-oviedo.jpg",
      "photoLocations": []
    },
    {
      "id": "wiley-smith",
      "name": "Wiley Smith",
      "description": "",
      "category": "interns",
      "individualPhoto": "/photos/individual/wiley-smith.jpg",
      "photoLocations": []
    },
    {
      "id": "michael-allen",
      "name": "Michael Allen",
      "description": "",
      "category": "staff",
      "individualPhoto": "/photos/individual/michael-allen.jpg",
      "photoLocations": []
    },
    {
      "id": "allison-chouinard",
      "name": "Allison Chouinard",
      "description": "",
      "category": "staff",
      "individualPhoto": "/photos/individual/allison-chouinard.jpg",
      "photoLocations": [],
      "linkedIn": "https://www.linkedin.com/in/allison-chouinard-med-pmp-02aa72239/"
    },
    {
      "id": "amanda-dobbs",
      "name": "Amanda Dobbs",
      "description": "",
      "category": "staff",
      "individualPhoto": "/photos/individual/amanda-dobbs.jpg",
      "photoLocations": [],
      "linkedIn": "https://www.linkedin.com/in/amanda-dobbs-132a5a63/"
    },
    {
      "id": "laura-means-kiker",
      "name": "Laura (Means) Kiker",
      "description": "",
      "category": "staff",
      "individualPhoto": "/photos/individual/laura-means-kiker.jpg",
      "photoLocations": [],
      "linkedIn": "https://www.linkedin.com/in/lmeanswell/"
    },
    {
      "id": "jaclyn-mcdougal-stursma",
      "name": "Jaclyn (McDougal) Stursma",
      "description": "",
      "category": "staff",
      "individualPhoto": "/photos/individual/jaclyn-mcdougal-stursma.jpg",
      "photoLocations": [],
      "linkedIn": "https://www.linkedin.com/in/jaclyn-stursma-4844865/"
    },
    {
      "id": "adam-farragut",
      "name": "Adam Farragut",
      "description": "",
      "category": "staff",
      "individualPhoto": "/photos/individual/adam-farragut.jpg",
      "photoLocations": [],
      "linkedIn": "https://www.linkedin.com/in/adam-farragut-32654b167/"
    },
    {
      "id": "twila-griggs-schneider",
      "name": "Twila Griggs Schneider",
      "description": "",
      "category": "staff",
      "individualPhoto": "/photos/individual/twila-schneider.jpg",
      "photoLocations": [],
      "linkedIn": "https://www.linkedin.com/in/twila-griggs-schneider-6b131922/"
    },
    {
      "id": "stephen-gabrys",
      "name": "Stephen Gabrys",
      "description": "",
      "category": "sil-lab",
      "individualPhoto": "/photos/individual/stephen-gabrys.jpg",
      "photoLocations": [],
      "linkedIn": "https://www.linkedin.com/in/stevexgabrys/"
    },
    {
      "id": "dalila-pugh",
      "name": "Dalila Pugh",
      "description": "",
      "category": "sil-lab",
      "individualPhoto": "/photos/individual/dalila-pugh.jpg",
      "photoLocations": [],
      "linkedIn": "https://www.linkedin.com/in/dalila-pugh-4546611/"
    },
    {
      "id": "grant-arndt",
      "name": "Grant Arndt",
      "description": "",
      "category": "sil-lab",
      "individualPhoto": "/photos/individual/grant-arndt.jpg",
      "photoLocations": [],
      "linkedIn": "https://www.linkedin.com/in/grant-arndt/"
    },
    {
      "id": "ejemole-michael-ojukwu",
      "name": "Ejemole (Michael) Ojukwu",
      "description": "",
      "category": "sil-lab",
      "individualPhoto": "/photos/individual/ejemole-michael-ojukwu.jpg",
      "photoLocations": [],
      "linkedIn": "https://www.linkedin.com/in/ejemole-ojukwu-2092a82b/"
    },
    {
      "id": "hannah-boulware",
      "name": "Hannah Boulware",
      "description": "",
      "category": "sil-lab",
      "individualPhoto": "/photos/individual/hannah-boulware.jpg",
      "photoLocations": [],
      "linkedIn": "https://www.linkedin.com/in/hannah-boulware-a3a44b251/"
    },
    {
      "id": "joe",
      "name": "Joe",
      "description": "So far away from home, Joe was the one person who knew the town that I grew up in.",
      "category": "sil-lab",
      "individualPhoto": "/photos/individual/joe.jpg",
      "photoLocations": []
    },
    {
      "id": "dan-mitchell",
      "name": "Dan Mitchell",
      "description": "",
      "category": "sil-lab",
      "individualPhoto": "/photos/individual/dan-mitchell.jpg",
      "photoLocations": []
    },
    {
      "id": "lakiesha-hawkins",
      "name": "Lakiesha Hawkins",
      "description": "",
      "category": "sil-lab",
      "individualPhoto": "/photos/individual/lakiesha-hawkins.jpg",
      "photoLocations": []
    }
  ],
  "groupPhotos": [
    {
      "id": "staff-photo",
      "name": "Pi Day!!",
      "imagePath": "/photos/staff-group.jpg",
      "category": "staff",
      "defaultZoom": 1.5
    },
    {
      "id": "interns-photo",
      "name": "All Hands",
      "imagePath": "/photos/interns-group.jpg",
      "category": "interns",
      "defaultZoom": 2.0,
      "zoomTranslation": { "x": 0, "y": -100 }
    },
    {
      "id": "family-photo",
      "name": "Family Visit",
      "imagePath": "/photos/family-group.jpg",
      "category": "staff",
      "defaultZoom": 1.5
    },
    {
      "id": "pathways-photo",
      "name": "U.S. Space & Rocket Center",
      "imagePath": "/photos/pathways-group.jpg",
      "category": "interns",
      "defaultZoom": 1.5
    }
  ]
}